{
  "homework": [
    {
      "name": "Биология",
      "value": "\nДоделать практическую ([Источник](https://discord.com/channels/819341231397929003/819644406763618344/893497704834007100))"
    },
    {
      "name": "География",
      "value": "\nКонтурные карты стр. 4 ([Источник](https://discord.com/channels/819341231397929003/819644773660098621/893407541449613322))"
    }
  ],
  "schedule": {
    "description": "\n`1` Информ. 29\n`2` Информ. 29\n`3` География 40\n`4` Биология 40\n`5` Математика\n`6` Математика\n`7` Физическая культура (юн) – зал"
  }
}